Metadata-Version: 2.1
Name: feature-space
Version: 0.0.5
Summary: A module framework for constructing a network of features supporting each other, yet each feature is calculated only once.
Home-page: https://github.com/Shahaf-F-S/feature-space
Author: Shahaf Frank-Shapir
Author-email: shahaffrs@gmail.com
License: MIT
Classifier: Intended Audience :: Developers
Classifier: License :: OSI Approved :: MIT License
Classifier: Programming Language :: Python
Classifier: Programming Language :: Python :: 3
Classifier: Programming Language :: Python :: 3.11
Classifier: Programming Language :: Python :: 3.12
Classifier: Operating System :: OS Independent
Requires-Dist: pandas
Requires-Dist: numpy
Requires-Dist: dill
Provides-Extra: dev
